PolibasePersonNotificationAutomationService/__init__.py
PolibasePersonNotificationAutomationService/__main__.py
PolibasePersonNotificationAutomationService/api.py
PolibasePersonNotificationAutomationService/const.py
PolibasePersonNotificationAutomationService/service.py
pih_plb_ntfc_auto-0.15.dist-info/METADATA
pih_plb_ntfc_auto-0.15.dist-info/WHEEL
pih_plb_ntfc_auto-0.15.dist-info/entry_points.txt
pih_plb_ntfc_auto-0.15.dist-info/top_level.txt
pih_plb_ntfc_auto-0.15.dist-info/RECORD
