Metadata-Version: 2.1
Name: pih-plb_ntfc_auto
Version: 0.15
Summary: PIH Polibase person notification automation service package
Home-page: https://pacifichosp.com/
Author: Nikita Karachentsev
Author-email: it@pacifichosp.com
License: MIT
Requires-Dist: ipih
